translated2video/__init__.py
translated2video/main.py
translated2video/t2f.py
translated2video-0.1.1.dist-info/WHEEL
translated2video-0.1.1.dist-info/entry_points.txt
translated2video-0.1.1.dist-info/METADATA
translated2video-0.1.1.dist-info/RECORD
