Metadata-Version: 2.3
Name: translated2video
Version: 0.1.1
Summary: Add your description here
Author: Nouchi
Author-email: Nouchi <nouchipri@outlook.com>
Requires-Dist: click>=8.3.1
Requires-Dist: opencv-python>=4.11.0.86
Requires-Dist: rich>=14.2.0
Requires-Python: >=3.13
